gcode_simulator/__init__.py
gcode_simulator/cli.py
gcode_simulator/gcode_simulator.py
gcode_simulator/main.py
gcode_simulator/viz.py
gcode_simulator-0.2.1.dist-info/METADATA
gcode_simulator-0.2.1.dist-info/WHEEL
gcode_simulator-0.2.1.dist-info/entry_points.txt
gcode_simulator-0.2.1.dist-info/licenses/LICENSE
gcode_simulator-0.2.1.dist-info/RECORD
